sqlite3manager/__init__.py
sqlite3manager/manager.py
tests/__init__.py
tests/test_connect.py
sqlite3_manager-1.1.0.dist-info/METADATA
sqlite3_manager-1.1.0.dist-info/WHEEL
sqlite3_manager-1.1.0.dist-info/top_level.txt
sqlite3_manager-1.1.0.dist-info/RECORD
