Metadata-Version: 2.4
Name: sqlite3-manager
Version: 1.1.0
Summary: Este paquete proporciona una serie de funcionalidades para gestionar bases de datos SQLite3 de manera sencilla y estandarizada.
Home-page: https://github.com/SurivZ/sqlite3-manager
Author: SurivZ
Author-email: franklinserrano23@email.com
Classifier: Development Status :: 4 - Beta
Classifier: Intended Audience :: Developers
Classifier: License :: OSI Approved :: BSD License
Classifier: Operating System :: OS Independent
Classifier: Programming Language :: Python :: 3.10
Classifier: Programming Language :: Python :: 3.11
Classifier: Programming Language :: Python :: 3.12
Classifier: Programming Language :: Python :: 3.13
Classifier: Programming Language :: Python :: 3 :: Only
Classifier: Topic :: Software Development :: Libraries :: Python Modules
Requires-Python: >=3.10
Dynamic: author
Dynamic: author-email
Dynamic: classifier
Dynamic: description
Dynamic: description-content-type
Dynamic: home-page
Dynamic: requires-python
Dynamic: summary
